async_redis_rate_limiters/__init__.py
async_redis_rate_limiters/concurrency.py
async_redis_rate_limiters/memory.py
async_redis_rate_limiters/py.typed
async_redis_rate_limiters/adapters/__init__.py
async_redis_rate_limiters/adapters/redis.py
async_redis_rate_limiters/lua/__init__.py
async_redis_rate_limiters/lua/acquire.lua
async_redis_rate_limiters/lua/release.lua
async_redis_rate_limiters-0.1.2.dist-info/licenses/LICENSE
async_redis_rate_limiters-0.1.2.dist-info/METADATA
async_redis_rate_limiters-0.1.2.dist-info/WHEEL
async_redis_rate_limiters-0.1.2.dist-info/top_level.txt
async_redis_rate_limiters-0.1.2.dist-info/RECORD
