Metadata-Version: 2.4
Name: async-redis-rate-limiters
Version: 0.1.2
Summary: Rock solid async python generic distributed rate limiters (concurrency and time) backed by Redis.
Project-URL: Homepage, https://github.com/fabien-marty/async-redis-rate-limiters
Project-URL: Repository, https://github.com/fabien-marty/async-redis-rate-limiters.git
Requires-Python: >=3.10
License-File: LICENSE
Requires-Dist: redis>=6.2.0
Requires-Dist: tenacity>=9.1.2
Dynamic: license-file
